generatorappmaya/__init__.py
generatorappmaya/cli.py
generatorappmaya/generator.py
generatorappmaya/migrations/__init__.py
generatorappmaya/models/__init__.py
generatorappmaya/templates/app/admin.py.template
generatorappmaya/templates/app/apps.py.template
generatorappmaya/templates/app/models.py.template
generatorappmaya/templates/app/tests.py.template
generatorappmaya/templates/app/urls.py.template
generatorappmaya/templates/app/views.py.template
generatorappmaya/views/__init__.py
generatorappmaya-0.3.dist-info/METADATA
generatorappmaya-0.3.dist-info/WHEEL
generatorappmaya-0.3.dist-info/entry_points.txt
generatorappmaya-0.3.dist-info/top_level.txt
generatorappmaya-0.3.dist-info/RECORD
